trypackage/__init__.py
trypackage/__main__.py
trypackage/config.py
trypackage/core.py
trypackage-0.2.3.dist-info/DESCRIPTION.rst
trypackage-0.2.3.dist-info/METADATA
trypackage-0.2.3.dist-info/RECORD
trypackage-0.2.3.dist-info/WHEEL
trypackage-0.2.3.dist-info/entry_points.txt
trypackage-0.2.3.dist-info/metadata.json
trypackage-0.2.3.dist-info/top_level.txt
