Metadata-Version: 2.0
Name: trypackage
Version: 0.2.3
Summary: Awesome cli tool to try out python packages
Home-page: https://github.com/timofurrer/try
Author: Timo Furrer
Author-email: tuxtimo@gmail.com
License: MIT
Keywords: try,python,packages,pypi,github,interactive,console,ipython,versions,virtualenv
Platform: UNKNOWN
Classifier: Programming Language :: Python
Classifier: Programming Language :: Python :: 3
Classifier: Programming Language :: Python :: 3.4
Classifier: Programming Language :: Python :: 3.5
Classifier: Operating System :: OS Independent
Classifier: Environment :: Console
Classifier: License :: OSI Approved :: MIT License
Classifier: Intended Audience :: End Users/Desktop
Classifier: Topic :: Utilities
Requires-Dist: click
